{
  "lastUpdate": "2021-01-19T06:17:35.236Z",
  "earthquakes": [
    {
      "maxIntensity": "2",
      "issuedAt": "2021-01-18T20:50:00.000Z",
      "uuid": "20210118205019393-19054740",
      "regionName": "Miyagi-ken Oki",
      "magnitude": 4,
      "occurredAt": "2021-01-18T20:47:00.000Z",
      "location": {
        "decimal": {
          "latitude": 38.9,
          "longitude": 141.9
        },
        "sexagesimal": {
          "latitude": "38° 54' 00\"",
          "longitude": "141° 54' 00\""
        },
        "depth": 50
      },
      "lastUpdate": "2021-01-18T21:17:14.911Z",
      "url": "https://www.jma.go.jp/en/quake/20210118205019393-19054740.html"
    }
  ],
  "volcanoes": [],
  "reportFile": "202101190617.md"
}