{
  "lastUpdate": "2021-01-16T13:57:57.873Z",
  "earthquakes": [
    {
      "maxIntensity": "1",
      "issuedAt": "2021-01-16T04:40:00.000Z",
      "uuid": "20210116044001493-16133646",
      "regionName": "Kagoshima-wan",
      "magnitude": 2.2,
      "occurredAt": "2021-01-16T04:36:00.000Z",
      "location": {
        "decimal": {
          "latitude": 31.3,
          "longitude": 130.6
        },
        "sexagesimal": {
          "latitude": "31° 18' 00\"",
          "longitude": "130° 36' 00\""
        },
        "depth": null
      },
      "lastUpdate": "2021-01-16T04:57:40.633Z",
      "url": "https://www.jma.go.jp/en/quake/20210116044001493-16133646.html"
    }
  ],
  "volcanoes": [],
  "reportFile": "202101161357.md"
}